symmer/.DS_Store
symmer/.idea/.gitignore
symmer/.idea/inspectionProfiles/Project_Default.xml
symmer/.idea/inspectionProfiles/profiles_settings.xml
symmer/.idea/misc.xml
symmer/.idea/modules.xml
symmer/.idea/symmer.iml
symmer/.idea/vcs.xml
symmer/__init__.py
symmer/approximate/__init__.py
symmer/approximate/tensor_network.py
symmer/command_line.py
symmer/evolution/__init__.py
symmer/evolution/circuit_symmerlator.py
symmer/evolution/decomposition.py
symmer/evolution/exponentiation.py
symmer/evolution/gate_library.py
symmer/evolution/utils.py
symmer/evolution/variational_optimization.py
symmer/operators/__init__.py
symmer/operators/anticommuting_op.py
symmer/operators/base.py
symmer/operators/independent_op.py
symmer/operators/noncontextual_op.py
symmer/operators/utils.py
symmer/process_handler.py
symmer/projection/__init__.py
symmer/projection/base.py
symmer/projection/contextual_subspace.py
symmer/projection/qubit_subspace_manager.py
symmer/projection/qubit_tapering.py
symmer/projection/utils.py
symmer/utils.py
symmer-0.0.10.dist-info/LICENSE
symmer-0.0.10.dist-info/METADATA
symmer-0.0.10.dist-info/WHEEL
symmer-0.0.10.dist-info/RECORD
