Metadata-Version: 2.3
Name: symmer
Version: 0.0.10
Summary: 
License: MIT
Author: AlexisRalli
Author-email: rallilex@hotmail.co.uk
Requires-Python: >=3.10,<4
Classifier: License :: OSI Approved :: MIT License
Classifier: Programming Language :: Python :: 3
Classifier: Programming Language :: Python :: 3.10
Classifier: Programming Language :: Python :: 3.11
Classifier: Programming Language :: Python :: 3.12
Classifier: Programming Language :: Python :: 3.13
Requires-Dist: cirq-core (>=1.5.0,<2)
Requires-Dist: ncon (>=2.0.0,<3.0.0)
Requires-Dist: numba (>=0.61.0,<0.62.0)
Requires-Dist: numpy (>=2.1,<3)
Requires-Dist: openfermion (>=1.6.1,<2)
Requires-Dist: opt-einsum (>=3.3.0,<4.0.0)
Requires-Dist: qiskit (>=2.0.0,<3.0.0)
Requires-Dist: quimb (>=1.7.3,<2.0.0)
Requires-Dist: scipy (>=1.15.0,<2)
